.bumpversion.cfg
.cookiecutterrc
.coveragerc
.editorconfig
.travis.yml
AUTHORS.rst
CHANGELOG.rst
CONTRIBUTING.rst
LICENSE
MANIFEST.in
README.rst
setup.cfg
setup.py
tox.ini
ci/bootstrap.py
ci/templates/.travis.yml
ci/templates/tox.ini
docs/authors.rst
docs/changelog.rst
docs/conf.py
docs/contributing.rst
docs/index.rst
docs/installation.rst
docs/readme.rst
docs/requirements.txt
docs/spelling_wordlist.txt
docs/usage.rst
docs/reference/index.rst
docs/reference/zsl_openapi.rst
src/zsl_openapi/__init__.py
src/zsl_openapi/api.py
src/zsl_openapi/configuration.py
src/zsl_openapi/decorators.py
src/zsl_openapi/generator.py
src/zsl_openapi/module.py
src/zsl_openapi.egg-info/PKG-INFO
src/zsl_openapi.egg-info/SOURCES.txt
src/zsl_openapi.egg-info/dependency_links.txt
src/zsl_openapi.egg-info/not-zip-safe
src/zsl_openapi.egg-info/requires.txt
src/zsl_openapi.egg-info/top_level.txt
src/zsl_openapi/builders/__init__.py
src/zsl_openapi/builders/description_info.py
src/zsl_openapi/builders/models.py
src/zsl_openapi/builders/tasks.py
tests/__init__.py
tests/models.py
tests/models_cli.py
tests/test_cli.py
tests/test_fill.py
tests/test_generator.py
tests/test_model_definitions_builder.py
tests/yaml_test_case.py
tests/templates/test_cli_description_result_spec.yml
tests/templates/test_cli_description_spec.yml
tests/templates/test_generator_api_spec.yml