Metadata-Version: 1.1
Name: zsl-openapi
Version: 0.2.0
Summary: Generate OpenAPI specification out of your ZSL service.
Home-page: https://github.com/AtteqCom/zsl_openapi
Author: Martin Babka
Author-email: babka@atteq.com
License: BSD
Platform: UNKNOWN
Classifier: Development Status :: 5 - Production/Stable
Classifier: Intended Audience :: Developers
Classifier: License :: OSI Approved :: BSD License
Classifier: Operating System :: Unix
Classifier: Operating System :: POSIX
Classifier: Operating System :: Microsoft :: Windows
Classifier: Programming Language :: Python
Classifier: Programming Language :: Python :: 2.7
Classifier: Programming Language :: Python :: 3
Classifier: Programming Language :: Python :: 3.6
Classifier: Topic :: Utilities
